README.rst
setup.py
NoHotEncoder.egg-info/PKG-INFO
NoHotEncoder.egg-info/SOURCES.txt
NoHotEncoder.egg-info/dependency_links.txt
NoHotEncoder.egg-info/requires.txt
NoHotEncoder.egg-info/top_level.txt
nohotencoder/__init__.py
nohotencoder/encoder.py