Metadata-Version: 1.0
Name: NoHotEncoder
Version: 0.2
Summary: Converts One Hot Encoding to Integer encoding
Home-page: UNKNOWN
Author: Karishnu Poddar
Author-email: karishnu@gmail.com
License: MIT
Platform: UNKNOWN
